datai/__init__.py
datai/auto_plot.py
datai/data_cleaning.py
datai/gift.py
datai/utils.py
datai/visualization.py
datai-1.5.3.dist-info/METADATA
datai-1.5.3.dist-info/WHEEL
datai-1.5.3.dist-info/top_level.txt
datai-1.5.3.dist-info/RECORD
