Metadata-Version: 2.1
Name: datai
Version: 1.5.3
Summary: A library for data visualization and cleaning
Home-page: https://github.com/Anschoudary/datai
Author: M Ans
Author-email: m.ans.cs@outlook.com
Classifier: Programming Language :: Python :: 3
Classifier: Operating System :: OS Independent
Requires-Python: >=3.7
Requires-Dist: pandas
Requires-Dist: numpy
Requires-Dist: seaborn
Requires-Dist: matplotlib
Requires-Dist: setuptools
